[
  {
    "img": "building",
    "alt": [
      "A skyscraper shot from the ground, with the sky in the background."
    ],
    "longDesc": [
      "A New York City skyscraper shot from below. The sunny blue sky draws a stark contrast against the brown art deco architecture of the building. A distant plane and its long contrail can be seen passing against backdrop of the sky."
    ]
  },
  {
    "id": "gal02",
    "title": "City Gallery",
    "images": [
      "building",
      "skyline",
      "bridge"
    ]
  },
  {
    "img": "barGraph",
    "alt": "",
    "longDesc": ""
  }
]
